kolhalashon/__init__.py
kolhalashon/api.py
kolhalashon/models/__init__.py
kolhalashon/models/exceptions.py
kolhalashon/models/shiur.py
kolhalashon/utils/__init__.py
kolhalashon/utils/session_manager.py
kolhalashon-1.0.4.dist-info/METADATA
kolhalashon-1.0.4.dist-info/WHEEL
kolhalashon-1.0.4.dist-info/top_level.txt
kolhalashon-1.0.4.dist-info/RECORD
