Metadata-Version: 2.4
Name: kolhalashon
Version: 1.0.4
Summary: Python wrapper for Kol Halashon API
Home-page: https://github.com/ZviCode/KolHalashonApi
Author: zvi shteinman
Requires-Python: >=3.7
Requires-Dist: requests==2.32.3
Requires-Dist: python-dotenv==1.0.1
Dynamic: author
Dynamic: description
Dynamic: description-content-type
Dynamic: home-page
Dynamic: requires-dist
Dynamic: requires-python
Dynamic: summary
